spanish_dni/__init__.py
spanish_dni/constants.py
spanish_dni/control_digit.py
spanish_dni/dni.py
spanish_dni/generator/__init__.py
spanish_dni/generator/exceptions.py
spanish_dni/generator/generator.py
spanish_dni/validator/__init__.py
spanish_dni/validator/exceptions.py
spanish_dni/validator/validator.py
spanish_dni-1.0.3.dist-info/METADATA
spanish_dni-1.0.3.dist-info/WHEEL
spanish_dni-1.0.3.dist-info/top_level.txt
spanish_dni-1.0.3.dist-info/RECORD
