Metadata-Version: 2.1
Name: spanish-dni
Version: 1.0.3
Summary: Spanish DNI utilities for NIE/NIF
Author: Joan Travé
Author-email: jtravegordillo@gmail.com
License: MIT
Project-URL: Source, https://github.com/joanTrave/spanish_dni
Classifier: License :: OSI Approved :: MIT License
Classifier: Programming Language :: Python
Classifier: Programming Language :: Python :: 3
Requires-Python: >=3.8
